musicir/__init__.py
musicir/__main__.py
musicir/harmony/__init__.py
musicir/harmony/generation.py
musicir/harmony/scale.py
musicir/leadsheets/__init__.py
musicir/leadsheets/model.py
musicir/leadsheets/musicxml.py
musicir/py.typed
musicir/rhythm/__init__.py
musicir/rhythm/generate.py
musicir-0.0.6.dist-info/LICENSE.rst
musicir-0.0.6.dist-info/METADATA
musicir-0.0.6.dist-info/WHEEL
musicir-0.0.6.dist-info/entry_points.txt
musicir-0.0.6.dist-info/RECORD
