Metadata-Version: 2.3
Name: musicir
Version: 0.0.6
Summary: Music Information Retrieval
License: MIT
Author: Flávio Codeço Coelho
Author-email: fccoelho@gmail.com
Requires-Python: >=3.11,<3.13
Classifier: Development Status :: 2 - Pre-Alpha
Classifier: License :: OSI Approved :: MIT License
Classifier: Programming Language :: Python :: 3
Classifier: Programming Language :: Python :: 3.11
Classifier: Programming Language :: Python :: 3.12
Requires-Dist: SQLAlchemy[mypy] (>=1.4.35,<2.0.0)
Requires-Dist: click (>=8.0.1,<9.0.0)
Requires-Dist: jupyter (>=1.0.0,<2.0.0)
Requires-Dist: matplotlib (>=3.5.3,<4.0.0)
Requires-Dist: music21 (>=7.3.1,<8.0.0)
Requires-Dist: myst-parser (>=0.17.2,<0.18.0)
Requires-Dist: pretty_midi (>=0.2.9,<0.3.0)
Project-URL: Changelog, https://github.com/fccoelho/musicir/releases
Project-URL: Documentation, https://musicir.readthedocs.io
Project-URL: Homepage, https://github.com/fccoelho/musicir
Project-URL: Repository, https://github.com/fccoelho/musicir
